iscm/__init__.py
iscm/closed_form_data_generator.py
iscm/data_generator.py
iscm/data_genertaion_utils.py
iscm/data_sampler.py
iscm/graph_generator.py
iscm/graph_sampler.py
iscm/graph_utils.py
iscm/heuristic_data_generator.py
iscm/mechanisms/__init__.py
iscm/mechanisms/linear.py
iscm/mechanisms/rff.py
iscm-0.0.1.dist-info/licenses/LICENSE
iscm-0.0.1.dist-info/METADATA
iscm-0.0.1.dist-info/WHEEL
iscm-0.0.1.dist-info/top_level.txt
iscm-0.0.1.dist-info/RECORD
