Metadata-Version: 2.4
Name: iscm
Version: 0.0.1
Summary: A data generating package implemented as part of 'Standardizing Structural Causal Models'
Home-page: https://github.com/werkaaa/iscm
Author: Weronika Ormaniec
Author-email: wormaniec@ethz.ch
Classifier: Programming Language :: Python :: 3
Classifier: License :: OSI Approved :: MIT License
Classifier: Operating System :: OS Independent
Requires-Python: >=3.10
License-File: LICENSE
Requires-Dist: setuptools>=61.0
Requires-Dist: numpy>=1.24.4
Requires-Dist: igraph>=0.11.3
Requires-Dist: networkx>=2.8.2
Dynamic: author
Dynamic: author-email
Dynamic: classifier
Dynamic: home-page
Dynamic: license-file
Dynamic: requires-dist
Dynamic: requires-python
Dynamic: summary
